docs/conf.py
kingpin/__init__.py
kingpin/constants.py
kingpin/exceptions.py
kingpin/schema.py
kingpin/utils.py
kingpin/version.py
kingpin/actors/__init__.py
kingpin/actors/base.py
kingpin/actors/exceptions.py
kingpin/actors/group.py
kingpin/actors/hipchat.py
kingpin/actors/librato.py
kingpin/actors/misc.py
kingpin/actors/rollbar.py
kingpin/actors/utils.py
kingpin/actors/aws/__init__.py
kingpin/actors/aws/api_call_queue.py
kingpin/actors/aws/base.py
kingpin/actors/aws/cloudformation.py
kingpin/actors/aws/iam.py
kingpin/actors/aws/s3.py
kingpin/actors/aws/settings.py
kingpin/actors/aws/test/__init__.py
kingpin/actors/aws/test/integration_base.py
kingpin/actors/aws/test/integration_cloudformation.py
kingpin/actors/aws/test/integration_iam.py
kingpin/actors/aws/test/integration_s3.py
kingpin/actors/aws/test/test_api_call_queue.py
kingpin/actors/aws/test/test_base.py
kingpin/actors/aws/test/test_cloudformation.py
kingpin/actors/aws/test/test_iam.py
kingpin/actors/aws/test/test_s3.py
kingpin/actors/test/__init__.py
kingpin/actors/test/helper.py
kingpin/actors/test/integration_hipchat.py
kingpin/actors/test/integration_librato.py
kingpin/actors/test/integration_misc.py
kingpin/actors/test/integration_rollbar.py
kingpin/actors/test/test_base.py
kingpin/actors/test/test_group.py
kingpin/actors/test/test_hipchat.py
kingpin/actors/test/test_librato.py
kingpin/actors/test/test_misc.py
kingpin/actors/test/test_rollbar.py
kingpin/actors/test/test_utils.py
kingpin/bin/__init__.py
kingpin/bin/deploy.py
kingpin/bin/test/__init__.py
kingpin/bin/test/test_deploy.py
kingpin/test/__init__.py
kingpin/test/test_schema.py
kingpin/test/test_utils.py
kingpin/test/test_version.py
kingpin-5.0.0.dist-info/licenses/LICENSE
kingpin-5.0.0.dist-info/METADATA
kingpin-5.0.0.dist-info/WHEEL
kingpin-5.0.0.dist-info/entry_points.txt
kingpin-5.0.0.dist-info/top_level.txt
kingpin-5.0.0.dist-info/RECORD
